.DS_Store
bcitoolbox/BCIbox.py
bcitoolbox/BCIboxGUI.py
bcitoolbox/__init__.py
bcitoolbox/guifunc.py
bcitoolbox-0.1.0.6.dist-info/METADATA
bcitoolbox-0.1.0.6.dist-info/WHEEL
bcitoolbox-0.1.0.6.dist-info/top_level.txt
bcitoolbox-0.1.0.6.dist-info/RECORD
