Metadata-Version: 2.1
Name: bcitoolbox
Version: 0.1.0.6
Summary: A zero-programming package for Bayesian causal inference model
Author: evans.zhu
Author-email: evanszhu2001@gmail.com
Classifier: License :: OSI Approved :: MIT License
Classifier: Programming Language :: Python :: 3
Classifier: Programming Language :: Python :: 3.6
Classifier: Programming Language :: Python :: 3.7
Classifier: Programming Language :: Python :: 3.8
Classifier: Programming Language :: Python :: 3.9
Requires-Dist: numpy
Requires-Dist: matplotlib
Requires-Dist: scipy
Requires-Dist: pandas
Requires-Dist: scikit-learn
Requires-Dist: pyvbmc
Requires-Dist: requests
